.travis.yml
LICENSE.md
MANIFEST.in
Makefile
README.md
pylintrc
setup.cfg
setup.py
tox.ini
.tox/py36/pip-selfcheck.json
.tox/py36/lib/python3.6/no-global-site-packages.txt
.tox/py36/lib/python3.6/orig-prefix.txt
.tox/py36/lib/python3.6/site-packages/Flask-0.12.1.dist-info/LICENSE.txt
.tox/py36/lib/python3.6/site-packages/Flask-0.12.1.dist-info/entry_points.txt
.tox/py36/lib/python3.6/site-packages/Flask-0.12.1.dist-info/metadata.json
.tox/py36/lib/python3.6/site-packages/Flask-0.12.1.dist-info/top_level.txt
.tox/py36/lib/python3.6/site-packages/Flask_Cors-3.0.2.dist-info/metadata.json
.tox/py36/lib/python3.6/site-packages/Flask_Cors-3.0.2.dist-info/top_level.txt
.tox/py36/lib/python3.6/site-packages/Flask_Jsonpify-1.5.0.dist-info/metadata.json
.tox/py36/lib/python3.6/site-packages/Flask_Jsonpify-1.5.0.dist-info/top_level.txt
.tox/py36/lib/python3.6/site-packages/Jinja2-2.9.6.dist-info/LICENSE.txt
.tox/py36/lib/python3.6/site-packages/Jinja2-2.9.6.dist-info/entry_points.txt
.tox/py36/lib/python3.6/site-packages/Jinja2-2.9.6.dist-info/metadata.json
.tox/py36/lib/python3.6/site-packages/Jinja2-2.9.6.dist-info/top_level.txt
.tox/py36/lib/python3.6/site-packages/MarkupSafe-1.0.dist-info/LICENSE.txt
.tox/py36/lib/python3.6/site-packages/MarkupSafe-1.0.dist-info/metadata.json
.tox/py36/lib/python3.6/site-packages/MarkupSafe-1.0.dist-info/top_level.txt
.tox/py36/lib/python3.6/site-packages/PyYAML-3.12.dist-info/metadata.json
.tox/py36/lib/python3.6/site-packages/PyYAML-3.12.dist-info/top_level.txt
.tox/py36/lib/python3.6/site-packages/SQLAlchemy-1.1.9.dist-info/metadata.json
.tox/py36/lib/python3.6/site-packages/SQLAlchemy-1.1.9.dist-info/top_level.txt
.tox/py36/lib/python3.6/site-packages/Unidecode-0.04.20.dist-info/entry_points.txt
.tox/py36/lib/python3.6/site-packages/Unidecode-0.04.20.dist-info/metadata.json
.tox/py36/lib/python3.6/site-packages/Unidecode-0.04.20.dist-info/top_level.txt
.tox/py36/lib/python3.6/site-packages/Werkzeug-0.12.1.dist-info/LICENSE.txt
.tox/py36/lib/python3.6/site-packages/Werkzeug-0.12.1.dist-info/metadata.json
.tox/py36/lib/python3.6/site-packages/Werkzeug-0.12.1.dist-info/top_level.txt
.tox/py36/lib/python3.6/site-packages/amqp-2.1.4.dist-info/metadata.json
.tox/py36/lib/python3.6/site-packages/amqp-2.1.4.dist-info/top_level.txt
.tox/py36/lib/python3.6/site-packages/appdirs-1.4.3.dist-info/metadata.json
.tox/py36/lib/python3.6/site-packages/appdirs-1.4.3.dist-info/top_level.txt
.tox/py36/lib/python3.6/site-packages/awesome_slugify-1.6.5.dist-info/metadata.json
.tox/py36/lib/python3.6/site-packages/awesome_slugify-1.6.5.dist-info/top_level.txt
.tox/py36/lib/python3.6/site-packages/billiard-3.5.0.2.dist-info/metadata.json
.tox/py36/lib/python3.6/site-packages/billiard-3.5.0.2.dist-info/top_level.txt
.tox/py36/lib/python3.6/site-packages/bitarray-0.8.1.dist-info/metadata.json
.tox/py36/lib/python3.6/site-packages/bitarray-0.8.1.dist-info/top_level.txt
.tox/py36/lib/python3.6/site-packages/cachetools-2.0.0.dist-info/metadata.json
.tox/py36/lib/python3.6/site-packages/cachetools-2.0.0.dist-info/top_level.txt
.tox/py36/lib/python3.6/site-packages/cchardet-1.1.3.dist-info/metadata.json
.tox/py36/lib/python3.6/site-packages/cchardet-1.1.3.dist-info/top_level.txt
.tox/py36/lib/python3.6/site-packages/celery-4.0.2.dist-info/entry_points.txt
.tox/py36/lib/python3.6/site-packages/celery-4.0.2.dist-info/metadata.json
.tox/py36/lib/python3.6/site-packages/celery-4.0.2.dist-info/top_level.txt
.tox/py36/lib/python3.6/site-packages/click-6.7.dist-info/metadata.json
.tox/py36/lib/python3.6/site-packages/click-6.7.dist-info/top_level.txt
.tox/py36/lib/python3.6/site-packages/coverage-4.3.4.dist-info/entry_points.txt
.tox/py36/lib/python3.6/site-packages/coverage-4.3.4.dist-info/metadata.json
.tox/py36/lib/python3.6/site-packages/coverage-4.3.4.dist-info/top_level.txt
.tox/py36/lib/python3.6/site-packages/coverage/htmlfiles/index.html
.tox/py36/lib/python3.6/site-packages/coverage/htmlfiles/pyfile.html
.tox/py36/lib/python3.6/site-packages/datapackage-0.8.8.dist-info/metadata.json
.tox/py36/lib/python3.6/site-packages/datapackage-0.8.8.dist-info/top_level.txt
.tox/py36/lib/python3.6/site-packages/datapackage/schemas/csv-dialect-description-format.json
.tox/py36/lib/python3.6/site-packages/datapackage/schemas/data-package.json
.tox/py36/lib/python3.6/site-packages/datapackage/schemas/definitions.json
.tox/py36/lib/python3.6/site-packages/datapackage/schemas/fiscal-data-package.json
.tox/py36/lib/python3.6/site-packages/datapackage/schemas/json-table-schema.json
.tox/py36/lib/python3.6/site-packages/datapackage/schemas/tabular-data-package.json
.tox/py36/lib/python3.6/site-packages/datapackage_pipelines/VERSION
.tox/py36/lib/python3.6/site-packages/datapackage_pipelines-1.0.7.dist-info/entry_points.txt
.tox/py36/lib/python3.6/site-packages/datapackage_pipelines-1.0.7.dist-info/metadata.json
.tox/py36/lib/python3.6/site-packages/datapackage_pipelines-1.0.7.dist-info/top_level.txt
.tox/py36/lib/python3.6/site-packages/datapackage_pipelines/specs/schemas/pipeline-spec.schema.json
.tox/py36/lib/python3.6/site-packages/datapackage_pipelines/web/templates/dashboard.html
.tox/py36/lib/python3.6/site-packages/datapackage_pipelines_github/VERSION
.tox/py36/lib/python3.6/site-packages/datapackage_pipelines_github/schema.json
.tox/py36/lib/python3.6/site-packages/datapackage_pipelines_github-0.0.1.dist-info/metadata.json
.tox/py36/lib/python3.6/site-packages/datapackage_pipelines_github-0.0.1.dist-info/top_level.txt
.tox/py36/lib/python3.6/site-packages/et_xmlfile-1.0.1.dist-info/metadata.json
.tox/py36/lib/python3.6/site-packages/et_xmlfile-1.0.1.dist-info/top_level.txt
.tox/py36/lib/python3.6/site-packages/ezodf-0.3.2.dist-info/metadata.json
.tox/py36/lib/python3.6/site-packages/ezodf-0.3.2.dist-info/top_level.txt
.tox/py36/lib/python3.6/site-packages/future-0.16.0.dist-info/entry_points.txt
.tox/py36/lib/python3.6/site-packages/future-0.16.0.dist-info/metadata.json
