Metadata-Version: 1.1
Name: datapackage-pipelines-github
Version: 0.0.3
Summary: {{ DESCRIPTION }}
Home-page: https://github.com/frictionlessdata/datapackage-pipelines-github
Author: Open Knowledge Foundation
Author-email: info@okfn.org
License: MIT
Keywords: data
Platform: UNKNOWN
Classifier: Development Status :: 4 - Beta
Classifier: Environment :: Web Environment
Classifier: Intended Audience :: Developers
Classifier: License :: OSI Approved :: MIT License
Classifier: Operating System :: OS Independent
Classifier: Programming Language :: Python :: 2
Classifier: Programming Language :: Python :: 2.7
Classifier: Programming Language :: Python :: 3
Classifier: Programming Language :: Python :: 3.3
Classifier: Programming Language :: Python :: 3.4
Classifier: Programming Language :: Python :: 3.5
Classifier: Topic :: Internet :: WWW/HTTP :: Dynamic Content
Classifier: Topic :: Software Development :: Libraries :: Python Modules
